toqito/__init__.py
toqito/channel_metrics/__init__.py
toqito/channel_metrics/channel_distinguishability.py
toqito/channel_metrics/channel_fidelity.py
toqito/channel_metrics/completely_bounded_spectral_norm.py
toqito/channel_metrics/completely_bounded_trace_norm.py
toqito/channel_metrics/diamond_distance.py
toqito/channel_metrics/fidelity_of_separability.py
toqito/channel_metrics/tests/__init__.py
toqito/channel_metrics/tests/test_channel_distinguishability.py
toqito/channel_metrics/tests/test_channel_fidelity.py
toqito/channel_metrics/tests/test_completely_bounded_spectral_norm.py
toqito/channel_metrics/tests/test_completely_bounded_trace_norm.py
toqito/channel_metrics/tests/test_diamond_distance.py
toqito/channel_metrics/tests/test_fidelity_of_separability.py
toqito/channel_ops/__init__.py
toqito/channel_ops/apply_channel.py
toqito/channel_ops/choi_to_kraus.py
toqito/channel_ops/complementary_channel.py
toqito/channel_ops/dual_channel.py
toqito/channel_ops/kraus_to_choi.py
toqito/channel_ops/natural_representation.py
toqito/channel_ops/partial_channel.py
toqito/channel_ops/tests/__init__.py
toqito/channel_ops/tests/test_apply_channel.py
toqito/channel_ops/tests/test_choi_to_kraus.py
toqito/channel_ops/tests/test_complementary_channel.py
toqito/channel_ops/tests/test_dual_channel.py
toqito/channel_ops/tests/test_kraus_to_choi.py
toqito/channel_ops/tests/test_natural_representataion.py
toqito/channel_ops/tests/test_partial_channel.py
toqito/channel_props/__init__.py
toqito/channel_props/choi_rank.py
toqito/channel_props/is_completely_positive.py
toqito/channel_props/is_extremal.py
toqito/channel_props/is_herm_preserving.py
toqito/channel_props/is_positive.py
toqito/channel_props/is_quantum_channel.py
toqito/channel_props/is_trace_preserving.py
toqito/channel_props/is_unital.py
toqito/channel_props/is_unitary.py
toqito/channel_props/tests/__init__.py
toqito/channel_props/tests/test_choi_rank.py
toqito/channel_props/tests/test_is_completely_positive.py
toqito-1.1.3.dist-info/licenses/LICENSE
toqito-1.1.3.dist-info/METADATA
toqito-1.1.3.dist-info/WHEEL
toqito-1.1.3.dist-info/top_level.txt
toqito-1.1.3.dist-info/RECORD
