Metadata-Version: 2.4
Name: toqito
Version: 1.1.3
Summary: Python tools for the study of quantum information.
Author-email: Vincent Russo <vincentrusso1@gmail.com>
Maintainer-email: Vincent Russo <vincentrusso1@gmail.com>, Purva Thakre <quantum.purvat@gmail.com>
Project-URL: homepage, https://vprusso.github.io/toqito/
Project-URL: repository, https://github.com/vprusso/toqito
Keywords: quantum information,quantum computing,nonlocal games
Classifier: Development Status :: 5 - Production/Stable
Classifier: Intended Audience :: Science/Research
Classifier: Topic :: Scientific/Engineering :: Physics
Classifier: Topic :: Scientific/Engineering :: Quantum Computing
Classifier: Programming Language :: Python :: 3
Classifier: Programming Language :: Python :: 3.10
Classifier: Programming Language :: Python :: 3.11
Classifier: Programming Language :: Python :: 3.12
Classifier: License :: OSI Approved :: BSD License
Classifier: Operating System :: OS Independent
Requires-Python: <4,>=3.10
License-File: LICENSE
Requires-Dist: cvxpy==1.7.1
Requires-Dist: more-itertools==10.8.0
Requires-Dist: numpy==2.2.6
Requires-Dist: scipy==1.15.3
Requires-Dist: scs==3.2.7.post2
Requires-Dist: picos==2.6.0
Requires-Dist: networkx<4.0,>=3.4
Requires-Dist: numba<0.63.0,>=0.62.0
Requires-Dist: jupyter-sphinx<0.6.0,>=0.5.3
Requires-Dist: matplotlib==3.10.1
Dynamic: license-file
